{
    "@context": "http://iiif.io/api/presentation/2/context.json",
    "@id": "https://nakamura196.github.io/jpsearch/data/genji/manifest/18.xml",
    "@type": "sc:Manifest",
    "attribution": "国文学研究資料館",
    "label": "源氏物語 第18冊",
    "license": "https://creativecommons.org/licenses/by-sa/4.0/deed.ja",
    "metadata": [
        {
            "label": "Author",
            "value": "紫式部"
        },
        {
            "label": "Title",
            "value": "源氏物語"
        },
        {
            "label": "Date",
            "value": "八尾/勘兵衛(やお/かんべえ)〈洛陽〉 承応3"
        },
        {
            "label": "DOI",
            "value": "10.20730/200003803"
        }
    ],
    "sequences": [
        {
            "@id": "https://kotenseki.nijl.ac.jp/biblio/200003803/sequence/normal",
            "@type": "sc:Sequence",
            "canvases": [
                {
                    "@id": "https://kotenseki.nijl.ac.jp/biblio/200003803/canvas/604",
                    "@type": "sc:Canvas",
                    "height": 3744,
                    "images": [
                        {
                            "@id": "https://kotenseki.nijl.ac.jp/biblio/200003803/annotation/604",
                            "@type": "oa:Annotation",
                            "motivation": "sc:painting",
                            "on": "https://kotenseki.nijl.ac.jp/biblio/200003803/canvas/604",
                            "resource": {
                                "@id": "https://kotenseki.nijl.ac.jp/api/iiif/200003803/v4/NIIP/SA4-0026/SA4-0026-00604.tif/full/full/0/default.jpg",
                                "@type": "dctypes:Image",
                                "dc:identifier": "SA4-0026",
                                "format": "image/jpeg",
                                "height": 3744,
                                "service": {
                                    "@context": "http://iiif.io/api/image/2/context.json",
                                    "@id": "https://kotenseki.nijl.ac.jp/api/iiif/200003803/v4/NIIP/SA4-0026/SA4-0026-00604.tif",
                                    "profile": "http://iiif.io/api/image/2/level1.json"
                                },
                                "width": 5616
                            }
                        }
                    ],
                    "label": "604",
                    "width": 5616
                },
                {
                    "@id": "https://kotenseki.nijl.ac.jp/biblio/200003803/canvas/605",
                    "@type": "sc:Canvas",
                    "height": 3744,
                    "images": [
                        {
                            "@id": "https://kotenseki.nijl.ac.jp/biblio/200003803/annotation/605",
                            "@type": "oa:Annotation",
                            "motivation": "sc:painting",
                            "on": "https://kotenseki.nijl.ac.jp/biblio/200003803/canvas/605",
                            "resource": {
                                "@id": "https://kotenseki.nijl.ac.jp/api/iiif/200003803/v4/NIIP/SA4-0026/SA4-0026-00605.tif/full/full/0/default.jpg",
                                "@type": "dctypes:Image",
                                "dc:identifier": "SA4-0026",
                                "format": "image/jpeg",
                                "height": 3744,
                                "service": {
                                    "@context": "http://iiif.io/api/image/2/context.json",
                                    "@id": "https://kotenseki.nijl.ac.jp/api/iiif/200003803/v4/NIIP/SA4-0026/SA4-0026-00605.tif",
                                    "profile": "http://iiif.io/api/image/2/level1.json"
                                },
                                "width": 5616
                            }
                        }
                    ],
                    "label": "605",
                    "width": 5616
                },
                {
                    "@id": "https://kotenseki.nijl.ac.jp/biblio/200003803/canvas/606",
                    "@type": "sc:Canvas",
                    "height": 3744,
                    "images": [
                        {
                            "@id": "https://kotenseki.nijl.ac.jp/biblio/200003803/annotation/606",
                            "@type": "oa:Annotation",
                            "motivation": "sc:painting",
                            "on": "https://kotenseki.nijl.ac.jp/biblio/200003803/canvas/606",
                            "resource": {
                                "@id": "https://kotenseki.nijl.ac.jp/api/iiif/200003803/v4/NIIP/SA4-0026/SA4-0026-00606.tif/full/full/0/default.jpg",
                                "@type": "dctypes:Image",
                                "dc:identifier": "SA4-0026",
                                "format": "image/jpeg",
                                "height": 3744,
                                "service": {
                                    "@context": "http://iiif.io/api/image/2/context.json",
                                    "@id": "https://kotenseki.nijl.ac.jp/api/iiif/200003803/v4/NIIP/SA4-0026/SA4-0026-00606.tif",
                                    "profile": "http://iiif.io/api/image/2/level1.json"
                                },
                                "width": 5616
                            }
                        }
                    ],
                    "label": "606",
                    "width": 5616
                },
                {
                    "@id": "https://kotenseki.nijl.ac.jp/biblio/200003803/canvas/607",
                    "@type": "sc:Canvas",
                    "height": 3744,
                    "images": [
                        {
                            "@id": "https://kotenseki.nijl.ac.jp/biblio/200003803/annotation/607",
                            "@type": "oa:Annotation",
                            "motivation": "sc:painting",
                            "on": "https://kotenseki.nijl.ac.jp/biblio/200003803/canvas/607",
                            "resource": {
                                "@id": "https://kotenseki.nijl.ac.jp/api/iiif/200003803/v4/NIIP/SA4-0026/SA4-0026-00607.tif/full/full/0/default.jpg",
                                "@type": "dctypes:Image",
                                "dc:identifier": "SA4-0026",
                                "format": "image/jpeg",
                                "height": 3744,
                                "service": {
                                    "@context": "http://iiif.io/api/image/2/context.json",
                                    "@id": "https://kotenseki.nijl.ac.jp/api/iiif/200003803/v4/NIIP/SA4-0026/SA4-0026-00607.tif",
                                    "profile": "http://iiif.io/api/image/2/level1.json"
                                },
                                "width": 5616
                            }
                        }
                    ],
                    "label": "607",
                    "width": 5616
                },
                {
                    "@id": "https://kotenseki.nijl.ac.jp/biblio/200003803/canvas/608",
                    "@type": "sc:Canvas",
                    "height": 3744,
                    "images": [
                        {
                            "@id": "https://kotenseki.nijl.ac.jp/biblio/200003803/annotation/608",
                            "@type": "oa:Annotation",
                            "motivation": "sc:painting",
                            "on": "https://kotenseki.nijl.ac.jp/biblio/200003803/canvas/608",
                            "resource": {
                                "@id": "https://kotenseki.nijl.ac.jp/api/iiif/200003803/v4/NIIP/SA4-0026/SA4-0026-00608.tif/full/full/0/default.jpg",
                                "@type": "dctypes:Image",
                                "dc:identifier": "SA4-0026",
                                "format": "image/jpeg",
                                "height": 3744,
                                "service": {
                                    "@context": "http://iiif.io/api/image/2/context.json",
                                    "@id": "https://kotenseki.nijl.ac.jp/api/iiif/200003803/v4/NIIP/SA4-0026/SA4-0026-00608.tif",
                                    "profile": "http://iiif.io/api/image/2/level1.json"
                                },
                                "width": 5616
                            }
                        }
                    ],
                    "label": "608",
                    "width": 5616
                },
                {
                    "@id": "https://kotenseki.nijl.ac.jp/biblio/200003803/canvas/609",
                    "@type": "sc:Canvas",
                    "height": 3744,
                    "images": [
                        {
                            "@id": "https://kotenseki.nijl.ac.jp/biblio/200003803/annotation/609",
                            "@type": "oa:Annotation",
                            "motivation": "sc:painting",
                            "on": "https://kotenseki.nijl.ac.jp/biblio/200003803/canvas/609",
                            "resource": {
                                "@id": "https://kotenseki.nijl.ac.jp/api/iiif/200003803/v4/NIIP/SA4-0026/SA4-0026-00609.tif/full/full/0/default.jpg",
                                "@type": "dctypes:Image",
                                "dc:identifier": "SA4-0026",
                                "format": "image/jpeg",
                                "height": 3744,
                                "service": {
                                    "@context": "http://iiif.io/api/image/2/context.json",
                                    "@id": "https://kotenseki.nijl.ac.jp/api/iiif/200003803/v4/NIIP/SA4-0026/SA4-0026-00609.tif",
                                    "profile": "http://iiif.io/api/image/2/level1.json"
                                },
                                "width": 5616
                            }
                        }
                    ],
                    "label": "609",
                    "width": 5616
                },
                {
                    "@id": "https://kotenseki.nijl.ac.jp/biblio/200003803/canvas/610",
                    "@type": "sc:Canvas",
                    "height": 3744,
                    "images": [
                        {
                            "@id": "https://kotenseki.nijl.ac.jp/biblio/200003803/annotation/610",
                            "@type": "oa:Annotation",
                            "motivation": "sc:painting",
                            "on": "https://kotenseki.nijl.ac.jp/biblio/200003803/canvas/610",
                            "resource": {
                                "@id": "https://kotenseki.nijl.ac.jp/api/iiif/200003803/v4/NIIP/SA4-0026/SA4-0026-00610.tif/full/full/0/default.jpg",
                                "@type": "dctypes:Image",
                                "dc:identifier": "SA4-0026",
                                "format": "image/jpeg",
                                "height": 3744,
                                "service": {
                                    "@context": "http://iiif.io/api/image/2/context.json",
                                    "@id": "https://kotenseki.nijl.ac.jp/api/iiif/200003803/v4/NIIP/SA4-0026/SA4-0026-00610.tif",
                                    "profile": "http://iiif.io/api/image/2/level1.json"
                                },
                                "width": 5616
                            }
                        }
                    ],
                    "label": "610",
                    "width": 5616
                },
                {
                    "@id": "https://kotenseki.nijl.ac.jp/biblio/200003803/canvas/611",
                    "@type": "sc:Canvas",
                    "height": 3744,
                    "images": [
                        {
                            "@id": "https://kotenseki.nijl.ac.jp/biblio/200003803/annotation/611",
                            "@type": "oa:Annotation",
                            "motivation": "sc:painting",
                            "on": "https://kotenseki.nijl.ac.jp/biblio/200003803/canvas/611",
                            "resource": {
                                "@id": "https://kotenseki.nijl.ac.jp/api/iiif/200003803/v4/NIIP/SA4-0026/SA4-0026-00611.tif/full/full/0/default.jpg",
                                "@type": "dctypes:Image",
                                "dc:identifier": "SA4-0026",
                                "format": "image/jpeg",
                                "height": 3744,
                                "service": {
                                    "@context": "http://iiif.io/api/image/2/context.json",
                                    "@id": "https://kotenseki.nijl.ac.jp/api/iiif/200003803/v4/NIIP/SA4-0026/SA4-0026-00611.tif",
                                    "profile": "http://iiif.io/api/image/2/level1.json"
                                },
                                "width": 5616
                            }
                        }
                    ],
                    "label": "611",
                    "width": 5616
                },
                {
                    "@id": "https://kotenseki.nijl.ac.jp/biblio/200003803/canvas/612",
                    "@type": "sc:Canvas",
                    "height": 3744,
                    "images": [
                        {
                            "@id": "https://kotenseki.nijl.ac.jp/biblio/200003803/annotation/612",
                            "@type": "oa:Annotation",
                            "motivation": "sc:painting",
                            "on": "https://kotenseki.nijl.ac.jp/biblio/200003803/canvas/612",
                            "resource": {
                                "@id": "https://kotenseki.nijl.ac.jp/api/iiif/200003803/v4/NIIP/SA4-0026/SA4-0026-00612.tif/full/full/0/default.jpg",
                                "@type": "dctypes:Image",
                                "dc:identifier": "SA4-0026",
                                "format": "image/jpeg",
                                "height": 3744,
                                "service": {
                                    "@context": "http://iiif.io/api/image/2/context.json",
                                    "@id": "https://kotenseki.nijl.ac.jp/api/iiif/200003803/v4/NIIP/SA4-0026/SA4-0026-00612.tif",
                                    "profile": "http://iiif.io/api/image/2/level1.json"
                                },
                                "width": 5616
                            }
                        }
                    ],
                    "label": "612",
                    "width": 5616
                },
                {
                    "@id": "https://kotenseki.nijl.ac.jp/biblio/200003803/canvas/613",
                    "@type": "sc:Canvas",
                    "height": 3744,
                    "images": [
                        {
                            "@id": "https://kotenseki.nijl.ac.jp/biblio/200003803/annotation/613",
                            "@type": "oa:Annotation",
                            "motivation": "sc:painting",
                            "on": "https://kotenseki.nijl.ac.jp/biblio/200003803/canvas/613",
                            "resource": {
                                "@id": "https://kotenseki.nijl.ac.jp/api/iiif/200003803/v4/NIIP/SA4-0026/SA4-0026-00613.tif/full/full/0/default.jpg",
                                "@type": "dctypes:Image",
                                "dc:identifier": "SA4-0026",
                                "format": "image/jpeg",
                                "height": 3744,
                                "service": {
                                    "@context": "http://iiif.io/api/image/2/context.json",
                                    "@id": "https://kotenseki.nijl.ac.jp/api/iiif/200003803/v4/NIIP/SA4-0026/SA4-0026-00613.tif",
                                    "profile": "http://iiif.io/api/image/2/level1.json"
                                },
                                "width": 5616
                            }
                        }
                    ],
                    "label": "613",
                    "width": 5616
                },
                {
                    "@id": "https://kotenseki.nijl.ac.jp/biblio/200003803/canvas/614",
                    "@type": "sc:Canvas",
                    "height": 3744,
                    "images": [
                        {
                            "@id": "https://kotenseki.nijl.ac.jp/biblio/200003803/annotation/614",
                            "@type": "oa:Annotation",
                            "motivation": "sc:painting",
                            "on": "https://kotenseki.nijl.ac.jp/biblio/200003803/canvas/614",
                            "resource": {
                                "@id": "https://kotenseki.nijl.ac.jp/api/iiif/200003803/v4/NIIP/SA4-0026/SA4-0026-00614.tif/full/full/0/default.jpg",
                                "@type": "dctypes:Image",
                                "dc:identifier": "SA4-0026",
                                "format": "image/jpeg",
                                "height": 3744,
                                "service": {
                                    "@context": "http://iiif.io/api/image/2/context.json",
                                    "@id": "https://kotenseki.nijl.ac.jp/api/iiif/200003803/v4/NIIP/SA4-0026/SA4-0026-00614.tif",
                                    "profile": "http://iiif.io/api/image/2/level1.json"
                                },
                                "width": 5616
                            }
                        }
                    ],
                    "label": "614",
                    "width": 5616
                },
                {
                    "@id": "https://kotenseki.nijl.ac.jp/biblio/200003803/canvas/615",
                    "@type": "sc:Canvas",
                    "height": 3744,
                    "images": [
                        {
                            "@id": "https://kotenseki.nijl.ac.jp/biblio/200003803/annotation/615",
                            "@type": "oa:Annotation",
                            "motivation": "sc:painting",
                            "on": "https://kotenseki.nijl.ac.jp/biblio/200003803/canvas/615",
                            "resource": {
                                "@id": "https://kotenseki.nijl.ac.jp/api/iiif/200003803/v4/NIIP/SA4-0026/SA4-0026-00615.tif/full/full/0/default.jpg",
                                "@type": "dctypes:Image",
                                "dc:identifier": "SA4-0026",
                                "format": "image/jpeg",
                                "height": 3744,
                                "service": {
                                    "@context": "http://iiif.io/api/image/2/context.json",
                                    "@id": "https://kotenseki.nijl.ac.jp/api/iiif/200003803/v4/NIIP/SA4-0026/SA4-0026-00615.tif",
                                    "profile": "http://iiif.io/api/image/2/level1.json"
                                },
                                "width": 5616
                            }
                        }
                    ],
                    "label": "615",
                    "width": 5616
                },
                {
                    "@id": "https://kotenseki.nijl.ac.jp/biblio/200003803/canvas/616",
                    "@type": "sc:Canvas",
                    "height": 3744,
                    "images": [
                        {
                            "@id": "https://kotenseki.nijl.ac.jp/biblio/200003803/annotation/616",
                            "@type": "oa:Annotation",
                            "motivation": "sc:painting",
                            "on": "https://kotenseki.nijl.ac.jp/biblio/200003803/canvas/616",
                            "resource": {
                                "@id": "https://kotenseki.nijl.ac.jp/api/iiif/200003803/v4/NIIP/SA4-0026/SA4-0026-00616.tif/full/full/0/default.jpg",
                                "@type": "dctypes:Image",
                                "dc:identifier": "SA4-0026",
                                "format": "image/jpeg",
                                "height": 3744,
                                "service": {
                                    "@context": "http://iiif.io/api/image/2/context.json",
                                    "@id": "https://kotenseki.nijl.ac.jp/api/iiif/200003803/v4/NIIP/SA4-0026/SA4-0026-00616.tif",
                                    "profile": "http://iiif.io/api/image/2/level1.json"
                                },
                                "width": 5616
                            }
                        }
                    ],
                    "label": "616",
                    "width": 5616
                },
                {
                    "@id": "https://kotenseki.nijl.ac.jp/biblio/200003803/canvas/617",
                    "@type": "sc:Canvas",
                    "height": 3744,
                    "images": [
                        {
                            "@id": "https://kotenseki.nijl.ac.jp/biblio/200003803/annotation/617",
                            "@type": "oa:Annotation",
                            "motivation": "sc:painting",
                            "on": "https://kotenseki.nijl.ac.jp/biblio/200003803/canvas/617",
                            "resource": {
                                "@id": "https://kotenseki.nijl.ac.jp/api/iiif/200003803/v4/NIIP/SA4-0026/SA4-0026-00617.tif/full/full/0/default.jpg",
                                "@type": "dctypes:Image",
                                "dc:identifier": "SA4-0026",
                                "format": "image/jpeg",
                                "height": 3744,
                                "service": {
                                    "@context": "http://iiif.io/api/image/2/context.json",
                                    "@id": "https://kotenseki.nijl.ac.jp/api/iiif/200003803/v4/NIIP/SA4-0026/SA4-0026-00617.tif",
                                    "profile": "http://iiif.io/api/image/2/level1.json"
                                },
                                "width": 5616
                            }
                        }
                    ],
                    "label": "617",
                    "width": 5616
                },
                {
                    "@id": "https://kotenseki.nijl.ac.jp/biblio/200003803/canvas/618",
                    "@type": "sc:Canvas",
                    "height": 3744,
                    "images": [
                        {
                            "@id": "https://kotenseki.nijl.ac.jp/biblio/200003803/annotation/618",
                            "@type": "oa:Annotation",
                            "motivation": "sc:painting",
                            "on": "https://kotenseki.nijl.ac.jp/biblio/200003803/canvas/618",
                            "resource": {
                                "@id": "https://kotenseki.nijl.ac.jp/api/iiif/200003803/v4/NIIP/SA4-0026/SA4-0026-00618.tif/full/full/0/default.jpg",
                                "@type": "dctypes:Image",
                                "dc:identifier": "SA4-0026",
                                "format": "image/jpeg",
                                "height": 3744,
                                "service": {
                                    "@context": "http://iiif.io/api/image/2/context.json",
                                    "@id": "https://kotenseki.nijl.ac.jp/api/iiif/200003803/v4/NIIP/SA4-0026/SA4-0026-00618.tif",
                                    "profile": "http://iiif.io/api/image/2/level1.json"
                                },
                                "width": 5616
                            }
                        }
                    ],
                    "label": "618",
                    "width": 5616
                },
                {
                    "@id": "https://kotenseki.nijl.ac.jp/biblio/200003803/canvas/619",
                    "@type": "sc:Canvas",
                    "height": 3744,
                    "images": [
                        {
                            "@id": "https://kotenseki.nijl.ac.jp/biblio/200003803/annotation/619",
                            "@type": "oa:Annotation",
                            "motivation": "sc:painting",
                            "on": "https://kotenseki.nijl.ac.jp/biblio/200003803/canvas/619",
                            "resource": {
                                "@id": "https://kotenseki.nijl.ac.jp/api/iiif/200003803/v4/NIIP/SA4-0026/SA4-0026-00619.tif/full/full/0/default.jpg",
                                "@type": "dctypes:Image",
                                "dc:identifier": "SA4-0026",
                                "format": "image/jpeg",
                                "height": 3744,
                                "service": {
                                    "@context": "http://iiif.io/api/image/2/context.json",
                                    "@id": "https://kotenseki.nijl.ac.jp/api/iiif/200003803/v4/NIIP/SA4-0026/SA4-0026-00619.tif",
                                    "profile": "http://iiif.io/api/image/2/level1.json"
                                },
                                "width": 5616
                            }
                        }
                    ],
                    "label": "619",
                    "width": 5616
                },
                {
                    "@id": "https://kotenseki.nijl.ac.jp/biblio/200003803/canvas/620",
                    "@type": "sc:Canvas",
                    "height": 3744,
                    "images": [
                        {
                            "@id": "https://kotenseki.nijl.ac.jp/biblio/200003803/annotation/620",
                            "@type": "oa:Annotation",
                            "motivation": "sc:painting",
                            "on": "https://kotenseki.nijl.ac.jp/biblio/200003803/canvas/620",
                            "resource": {
                                "@id": "https://kotenseki.nijl.ac.jp/api/iiif/200003803/v4/NIIP/SA4-0026/SA4-0026-00620.tif/full/full/0/default.jpg",
                                "@type": "dctypes:Image",
                                "dc:identifier": "SA4-0026",
                                "format": "image/jpeg",
                                "height": 3744,
                                "service": {
                                    "@context": "http://iiif.io/api/image/2/context.json",
                                    "@id": "https://kotenseki.nijl.ac.jp/api/iiif/200003803/v4/NIIP/SA4-0026/SA4-0026-00620.tif",
                                    "profile": "http://iiif.io/api/image/2/level1.json"
                                },
                                "width": 5616
                            }
                        }
                    ],
                    "label": "620",
                    "width": 5616
                },
                {
                    "@id": "https://kotenseki.nijl.ac.jp/biblio/200003803/canvas/621",
                    "@type": "sc:Canvas",
                    "height": 3744,
                    "images": [
                        {
                            "@id": "https://kotenseki.nijl.ac.jp/biblio/200003803/annotation/621",
                            "@type": "oa:Annotation",
                            "motivation": "sc:painting",
                            "on": "https://kotenseki.nijl.ac.jp/biblio/200003803/canvas/621",
                            "resource": {
                                "@id": "https://kotenseki.nijl.ac.jp/api/iiif/200003803/v4/NIIP/SA4-0026/SA4-0026-00621.tif/full/full/0/default.jpg",
                                "@type": "dctypes:Image",
                                "dc:identifier": "SA4-0026",
                                "format": "image/jpeg",
                                "height": 3744,
                                "service": {
                                    "@context": "http://iiif.io/api/image/2/context.json",
                                    "@id": "https://kotenseki.nijl.ac.jp/api/iiif/200003803/v4/NIIP/SA4-0026/SA4-0026-00621.tif",
                                    "profile": "http://iiif.io/api/image/2/level1.json"
                                },
                                "width": 5616
                            }
                        }
                    ],
                    "label": "621",
                    "width": 5616
                },
                {
                    "@id": "https://kotenseki.nijl.ac.jp/biblio/200003803/canvas/622",
                    "@type": "sc:Canvas",
                    "height": 3744,
                    "images": [
                        {
                            "@id": "https://kotenseki.nijl.ac.jp/biblio/200003803/annotation/622",
                            "@type": "oa:Annotation",
                            "motivation": "sc:painting",
                            "on": "https://kotenseki.nijl.ac.jp/biblio/200003803/canvas/622",
                            "resource": {
                                "@id": "https://kotenseki.nijl.ac.jp/api/iiif/200003803/v4/NIIP/SA4-0026/SA4-0026-00622.tif/full/full/0/default.jpg",
                                "@type": "dctypes:Image",
                                "dc:identifier": "SA4-0026",
                                "format": "image/jpeg",
                                "height": 3744,
                                "service": {
                                    "@context": "http://iiif.io/api/image/2/context.json",
                                    "@id": "https://kotenseki.nijl.ac.jp/api/iiif/200003803/v4/NIIP/SA4-0026/SA4-0026-00622.tif",
                                    "profile": "http://iiif.io/api/image/2/level1.json"
                                },
                                "width": 5616
                            }
                        }
                    ],
                    "label": "622",
                    "width": 5616
                },
                {
                    "@id": "https://kotenseki.nijl.ac.jp/biblio/200003803/canvas/623",
                    "@type": "sc:Canvas",
                    "height": 3744,
                    "images": [
                        {
                            "@id": "https://kotenseki.nijl.ac.jp/biblio/200003803/annotation/623",
                            "@type": "oa:Annotation",
                            "motivation": "sc:painting",
                            "on": "https://kotenseki.nijl.ac.jp/biblio/200003803/canvas/623",
                            "resource": {
                                "@id": "https://kotenseki.nijl.ac.jp/api/iiif/200003803/v4/NIIP/SA4-0026/SA4-0026-00623.tif/full/full/0/default.jpg",
                                "@type": "dctypes:Image",
                                "dc:identifier": "SA4-0026",
                                "format": "image/jpeg",
                                "height": 3744,
                                "service": {
                                    "@context": "http://iiif.io/api/image/2/context.json",
                                    "@id": "https://kotenseki.nijl.ac.jp/api/iiif/200003803/v4/NIIP/SA4-0026/SA4-0026-00623.tif",
                                    "profile": "http://iiif.io/api/image/2/level1.json"
                                },
                                "width": 5616
                            }
                        }
                    ],
                    "label": "623",
                    "width": 5616
                },
                {
                    "@id": "https://kotenseki.nijl.ac.jp/biblio/200003803/canvas/624",
                    "@type": "sc:Canvas",
                    "height": 3744,
                    "images": [
                        {
                            "@id": "https://kotenseki.nijl.ac.jp/biblio/200003803/annotation/624",
                            "@type": "oa:Annotation",
                            "motivation": "sc:painting",
                            "on": "https://kotenseki.nijl.ac.jp/biblio/200003803/canvas/624",
                            "resource": {
                                "@id": "https://kotenseki.nijl.ac.jp/api/iiif/200003803/v4/NIIP/SA4-0026/SA4-0026-00624.tif/full/full/0/default.jpg",
                                "@type": "dctypes:Image",
                                "dc:identifier": "SA4-0026",
                                "format": "image/jpeg",
                                "height": 3744,
                                "service": {
                                    "@context": "http://iiif.io/api/image/2/context.json",
                                    "@id": "https://kotenseki.nijl.ac.jp/api/iiif/200003803/v4/NIIP/SA4-0026/SA4-0026-00624.tif",
                                    "profile": "http://iiif.io/api/image/2/level1.json"
                                },
                                "width": 5616
                            }
                        }
                    ],
                    "label": "624",
                    "width": 5616
                },
                {
                    "@id": "https://kotenseki.nijl.ac.jp/biblio/200003803/canvas/625",
                    "@type": "sc:Canvas",
                    "height": 3744,
                    "images": [
                        {
                            "@id": "https://kotenseki.nijl.ac.jp/biblio/200003803/annotation/625",
                            "@type": "oa:Annotation",
                            "motivation": "sc:painting",
                            "on": "https://kotenseki.nijl.ac.jp/biblio/200003803/canvas/625",
                            "resource": {
                                "@id": "https://kotenseki.nijl.ac.jp/api/iiif/200003803/v4/NIIP/SA4-0026/SA4-0026-00625.tif/full/full/0/default.jpg",
                                "@type": "dctypes:Image",
                                "dc:identifier": "SA4-0026",
                                "format": "image/jpeg",
                                "height": 3744,
                                "service": {
                                    "@context": "http://iiif.io/api/image/2/context.json",
                                    "@id": "https://kotenseki.nijl.ac.jp/api/iiif/200003803/v4/NIIP/SA4-0026/SA4-0026-00625.tif",
                                    "profile": "http://iiif.io/api/image/2/level1.json"
                                },
                                "width": 5616
                            }
                        }
                    ],
                    "label": "625",
                    "width": 5616
                },
                {
                    "@id": "https://kotenseki.nijl.ac.jp/biblio/200003803/canvas/626",
                    "@type": "sc:Canvas",
                    "height": 3744,
                    "images": [
                        {
                            "@id": "https://kotenseki.nijl.ac.jp/biblio/200003803/annotation/626",
                            "@type": "oa:Annotation",
                            "motivation": "sc:painting",
                            "on": "https://kotenseki.nijl.ac.jp/biblio/200003803/canvas/626",
                            "resource": {
                                "@id": "https://kotenseki.nijl.ac.jp/api/iiif/200003803/v4/NIIP/SA4-0026/SA4-0026-00626.tif/full/full/0/default.jpg",
                                "@type": "dctypes:Image",
                                "dc:identifier": "SA4-0026",
                                "format": "image/jpeg",
                                "height": 3744,
                                "service": {
                                    "@context": "http://iiif.io/api/image/2/context.json",
                                    "@id": "https://kotenseki.nijl.ac.jp/api/iiif/200003803/v4/NIIP/SA4-0026/SA4-0026-00626.tif",
                                    "profile": "http://iiif.io/api/image/2/level1.json"
                                },
                                "width": 5616
                            }
                        }
                    ],
                    "label": "626",
                    "width": 5616
                },
                {
                    "@id": "https://kotenseki.nijl.ac.jp/biblio/200003803/canvas/627",
                    "@type": "sc:Canvas",
                    "height": 3744,
                    "images": [
                        {
                            "@id": "https://kotenseki.nijl.ac.jp/biblio/200003803/annotation/627",
                            "@type": "oa:Annotation",
                            "motivation": "sc:painting",
                            "on": "https://kotenseki.nijl.ac.jp/biblio/200003803/canvas/627",
                            "resource": {
                                "@id": "https://kotenseki.nijl.ac.jp/api/iiif/200003803/v4/NIIP/SA4-0026/SA4-0026-00627.tif/full/full/0/default.jpg",
                                "@type": "dctypes:Image",
                                "dc:identifier": "SA4-0026",
                                "format": "image/jpeg",
                                "height": 3744,
                                "service": {
                                    "@context": "http://iiif.io/api/image/2/context.json",
                                    "@id": "https://kotenseki.nijl.ac.jp/api/iiif/200003803/v4/NIIP/SA4-0026/SA4-0026-00627.tif",
                                    "profile": "http://iiif.io/api/image/2/level1.json"
                                },
                                "width": 5616
                            }
                        }
                    ],
                    "label": "627",
                    "width": 5616
                },
                {
                    "@id": "https://kotenseki.nijl.ac.jp/biblio/200003803/canvas/628",
                    "@type": "sc:Canvas",
                    "height": 3744,
                    "images": [
                        {
                            "@id": "https://kotenseki.nijl.ac.jp/biblio/200003803/annotation/628",
                            "@type": "oa:Annotation",
                            "motivation": "sc:painting",
                            "on": "https://kotenseki.nijl.ac.jp/biblio/200003803/canvas/628",
                            "resource": {
                                "@id": "https://kotenseki.nijl.ac.jp/api/iiif/200003803/v4/NIIP/SA4-0026/SA4-0026-00628.tif/full/full/0/default.jpg",
                                "@type": "dctypes:Image",
                                "dc:identifier": "SA4-0026",
                                "format": "image/jpeg",
                                "height": 3744,
                                "service": {
                                    "@context": "http://iiif.io/api/image/2/context.json",
                                    "@id": "https://kotenseki.nijl.ac.jp/api/iiif/200003803/v4/NIIP/SA4-0026/SA4-0026-00628.tif",
                                    "profile": "http://iiif.io/api/image/2/level1.json"
                                },
                                "width": 5616
                            }
                        }
                    ],
                    "label": "628",
                    "width": 5616
                }
            ]
        }
    ],
    "service": {
        "@context": "http://iiif.io/api/search/0/context.json",
        "@id": "https://iiif.dl.itc.u-tokyo.ac.jp/api/iiif-search/get.php/https://nakamura196.github.io/jpsearch/data/genji/tei/18.xml",
        "label": "Search within this manifest",
        "profile": "http://iiif.io/api/search/0/search"
    },
    "structures": [
        {
            "@id": "https://kotenseki.nijl.ac.jp/biblio/200003803/range/r18_cover.json",
            "@type": "sc:Range",
            "canvases": [
                "https://kotenseki.nijl.ac.jp/biblio/200003803/canvas/604"
            ],
            "label": "表紙",
            "within": "https://kotenseki.nijl.ac.jp/biblio/200003803/range/r18.json"
        },
        {
            "@id": "https://kotenseki.nijl.ac.jp/biblio/200003803/range/r18_pic1.json",
            "@type": "sc:Range",
            "canvases": [
                "https://kotenseki.nijl.ac.jp/biblio/200003803/canvas/613"
            ],
            "label": "挿絵[1]",
            "within": "https://kotenseki.nijl.ac.jp/biblio/200003803/range/r18.json"
        },
        {
            "@id": "https://kotenseki.nijl.ac.jp/biblio/200003803/range/r18_pic2.json",
            "@type": "sc:Range",
            "canvases": [
                "https://kotenseki.nijl.ac.jp/biblio/200003803/canvas/615"
            ],
            "label": "挿絵[2]",
            "within": "https://kotenseki.nijl.ac.jp/biblio/200003803/range/r18.json"
        },
        {
            "@id": "https://kotenseki.nijl.ac.jp/biblio/200003803/range/r18_pic3.json",
            "@type": "sc:Range",
            "canvases": [
                "https://kotenseki.nijl.ac.jp/biblio/200003803/canvas/622"
            ],
            "label": "挿絵[3]",
            "within": "https://kotenseki.nijl.ac.jp/biblio/200003803/range/r18.json"
        },
        {
            "@id": "https://kotenseki.nijl.ac.jp/biblio/200003803/range/r18_backcover.json",
            "@type": "sc:Range",
            "canvases": [
                "https://kotenseki.nijl.ac.jp/biblio/200003803/canvas/628"
            ],
            "label": "裏表紙",
            "within": "https://kotenseki.nijl.ac.jp/biblio/200003803/range/r18.json"
        }
    ],
    "viewingDirection": "right-to-left",
    "viewingHint": "paged"
}